api_tgbot/__init__.py
api_tgbot/tgbot.py
api_tgbot/tgbot_json.py
python_telegram_bot_api-0.0.7.dist-info/LICENSE
python_telegram_bot_api-0.0.7.dist-info/METADATA
python_telegram_bot_api-0.0.7.dist-info/WHEEL
python_telegram_bot_api-0.0.7.dist-info/top_level.txt
python_telegram_bot_api-0.0.7.dist-info/RECORD
