Metadata-Version: 2.1
Name: python-telegram-bot-api
Version: 0.0.7
Summary: Simple and fast client to call rest-api endpoints `api.telegram.org` using `aiohttp` package.
Home-page: https://github.com/DmitriyKalekin/python-telegram-bot-api
Author: Dmitriy Kalekin
Author-email: herrhorror@gmail.com
License: UNKNOWN
Project-URL: Source, https://github.com/DmitriyKalekin/python-telegram-bot-api
Keywords: pydantic telegram api bot
Platform: UNKNOWN
Classifier: Intended Audience :: Developers
Classifier: Programming Language :: Python :: 3.8
Classifier: Topic :: Software Development :: Build Tools
Classifier: License :: OSI Approved :: GNU Lesser General Public License v2 or later (LGPLv2+)
Classifier: Operating System :: OS Independent
Requires-Python: >=3.7, <4
Provides-Extra: test
